LICENSE
MANIFEST.in
README.rst
runtests.py
setup.py
micawber_bs4_classes/__init__.py
micawber_bs4_classes/cache.py
micawber_bs4_classes/compat.py
micawber_bs4_classes/exceptions.py
micawber_bs4_classes/parsers.py
micawber_bs4_classes/providers.py
micawber_bs4_classes/test_utils.py
micawber_bs4_classes/tests.py
micawber_bs4_classes.egg-info/PKG-INFO
micawber_bs4_classes.egg-info/SOURCES.txt
micawber_bs4_classes.egg-info/dependency_links.txt
micawber_bs4_classes.egg-info/requires.txt
micawber_bs4_classes.egg-info/top_level.txt
micawber_bs4_classes/contrib/__init__.py
micawber_bs4_classes/contrib/mcflask.py
micawber_bs4_classes/contrib/providers.py
micawber_bs4_classes/contrib/mcdjango/__init__.py
micawber_bs4_classes/contrib/mcdjango/models.py
micawber_bs4_classes/contrib/mcdjango/providers.py
micawber_bs4_classes/contrib/mcdjango/mcdjango_tests/__init__.py
micawber_bs4_classes/contrib/mcdjango/mcdjango_tests/models.py
micawber_bs4_classes/contrib/mcdjango/mcdjango_tests/tests.py
micawber_bs4_classes/contrib/mcdjango/templates/micawber_bs4_classes/link.html
micawber_bs4_classes/contrib/mcdjango/templates/micawber_bs4_classes/photo.html
micawber_bs4_classes/contrib/mcdjango/templates/micawber_bs4_classes/rich.html
micawber_bs4_classes/contrib/mcdjango/templates/micawber_bs4_classes/video.html
micawber_bs4_classes/contrib/mcdjango/templatetags/__init__.py
micawber_bs4_classes/contrib/mcdjango/templatetags/micawber_tags.py